{
	"name": "DynamicDataSet",
	"properties": {
		"linkedServiceName": {
			"referenceName": "AzureDataLakeStorage2",
			"type": "LinkedServiceReference"
		},
		"parameters": {
			"FileSystem": {
				"type": "String",
				"defaultValue": "dldemofilesystem"
			},
			"Directory": {
				"type": "String",
				"defaultValue": "Dataflow"
			},
			"Filename": {
				"type": "String",
				"defaultValue": "employee.csv"
			}
		},
		"annotations": [],
		"type": "DelimitedText",
		"typeProperties": {
			"location": {
				"type": "AzureBlobFSLocation",
				"fileName": {
					"value": "@dataset().Filename",
					"type": "Expression"
				},
				"folderPath": {
					"value": "@dataset().Directory",
					"type": "Expression"
				},
				"fileSystem": {
					"value": "@dataset().FileSystem",
					"type": "Expression"
				}
			},
			"columnDelimiter": ",",
			"escapeChar": "\\",
			"firstRowAsHeader": true,
			"quoteChar": "\""
		},
		"schema": []
	}
}